xmelutils/__init__.py
xmelutils/random_utils.py
xmelutils/str_utils.py
xmelutils-0.0.3.dist-info/licenses/LICENSE
xmelutils-0.0.3.dist-info/METADATA
xmelutils-0.0.3.dist-info/WHEEL
xmelutils-0.0.3.dist-info/top_level.txt
xmelutils-0.0.3.dist-info/RECORD
