Metadata-Version: 2.4
Name: xmelutils
Version: 0.0.3
Summary: Personal utility functions by Igor Xmelnikov. Developed for personal use but shared for anyone who might find them helpful. 
Home-page: https://github.com/GigaGitCoder/XmelUtils
Author: Igor Xmelnikov
Author-email: egorkholkin2018@gmail.com
License: MIT
Keywords: igor xmel utilities string tools
Classifier: Development Status :: 3 - Alpha
Classifier: Intended Audience :: Developers
Classifier: License :: OSI Approved :: MIT License
Classifier: Programming Language :: Python :: 3
Classifier: Topic :: Utilities
Requires-Python: >=3.6
License-File: LICENSE
Dynamic: author
Dynamic: author-email
Dynamic: classifier
Dynamic: description
Dynamic: description-content-type
Dynamic: home-page
Dynamic: keywords
Dynamic: license
Dynamic: license-file
Dynamic: requires-python
Dynamic: summary
